{
  "repeats": 5,
  "total_cases": 48,
  "summaries": [
    {
      "transport": "quic-datagram",
      "quality": "excellent",
      "payload": "large",
      "payload_bytes": 262144,
      "runs": 5,
      "events_per_s_p50": 50659.65199352063,
      "events_per_s_p95": 51148.213456839214,
      "elapsed_s_p95": 0.001119875,
      "sent_total": 0,
      "dropped_total": 0,
      "fallback_total": 200,
      "mode_switch_count_total": 0,
      "effective_parity_rate_p50": 0.0,
      "feedback_lag_ms_p95": 0.0,
      "closed_loop": false,
      "duplication_rate_p50": 0.0,
      "deadline_miss_rate_p95": 0.0,
      "tail_ratio_p99_p50": 1.0
    },
    {
      "transport": "quic-datagram",
      "quality": "excellent",
      "payload": "medium",
      "payload_bytes": 65536,
      "runs": 5,
      "events_per_s_p50": 85121.41505840393,
      "events_per_s_p95": 86276.62442706928,
      "elapsed_s_p95": 0.001096416,
      "sent_total": 0,
      "dropped_total": 1,
      "fallback_total": 199,
      "mode_switch_count_total": 0,
      "effective_parity_rate_p50": 0.0,
      "feedback_lag_ms_p95": 0.0,
      "closed_loop": false,
      "duplication_rate_p50": 0.0,
      "deadline_miss_rate_p95": 0.0,
      "tail_ratio_p99_p50": 1.0
    },
    {
      "transport": "quic-datagram",
      "quality": "excellent",
      "payload": "small",
      "payload_bytes": 4096,
      "runs": 5,
      "events_per_s_p50": 25769.725597519406,
      "events_per_s_p95": 51164.56955887187,
      "elapsed_s_p95": 0.002359125,
      "sent_total": 0,
      "dropped_total": 0,
      "fallback_total": 200,
      "mode_switch_count_total": 0,
      "effective_parity_rate_p50": 0.0,
      "feedback_lag_ms_p95": 0.0,
      "closed_loop": false,
      "duplication_rate_p50": 0.0,
      "deadline_miss_rate_p95": 0.0,
      "tail_ratio_p99_p50": 1.0
    },
    {
      "transport": "quic-datagram",
      "quality": "excellent",
      "payload": "tiny",
      "payload_bytes": 256,
      "runs": 5,
      "events_per_s_p50": 148998.54353923688,
      "events_per_s_p95": 153920.1539201539,
      "elapsed_s_p95": 0.003542708,
      "sent_total": 198,
      "dropped_total": 0,
      "fallback_total": 2,
      "mode_switch_count_total": 0,
      "effective_parity_rate_p50": 0.0,
      "feedback_lag_ms_p95": 0.0,
      "closed_loop": false,
      "duplication_rate_p50": 0.0,
      "deadline_miss_rate_p95": 0.0,
      "tail_ratio_p99_p50": 1.0
    },
    {
      "transport": "quic-datagram",
      "quality": "good",
      "payload": "large",
      "payload_bytes": 262144,
      "runs": 5,
      "events_per_s_p50": 352.2533758532512,
      "events_per_s_p95": 359.70347053059174,
      "elapsed_s_p95": 0.1169345,
      "sent_total": 0,
      "dropped_total": 1,
      "fallback_total": 199,
      "mode_switch_count_total": 0,
      "effective_parity_rate_p50": 0.0,
      "feedback_lag_ms_p95": 0.0,
      "closed_loop": false,
      "duplication_rate_p50": 0.0,
      "deadline_miss_rate_p95": 0.002,
      "tail_ratio_p99_p50": 1.006
    },
    {
      "transport": "quic-datagram",
      "quality": "good",
      "payload": "medium",
      "payload_bytes": 65536,
      "runs": 5,
      "events_per_s_p50": 355.1663185267218,
      "events_per_s_p95": 359.99793001190244,
      "elapsed_s_p95": 0.113411916,
      "sent_total": 0,
      "dropped_total": 1,
      "fallback_total": 199,
      "mode_switch_count_total": 0,
      "effective_parity_rate_p50": 0.0,
      "feedback_lag_ms_p95": 0.0,
      "closed_loop": false,
      "duplication_rate_p50": 0.0,
      "deadline_miss_rate_p95": 0.002,
      "tail_ratio_p99_p50": 1.006
    },
    {
      "transport": "quic-datagram",
      "quality": "good",
      "payload": "small",
      "payload_bytes": 4096,
      "runs": 5,
      "events_per_s_p50": 355.6534282176372,
      "events_per_s_p95": 362.23079618492005,
      "elapsed_s_p95": 0.113322834,
      "sent_total": 0,
      "dropped_total": 0,
      "fallback_total": 200,
      "mode_switch_count_total": 0,
      "effective_parity_rate_p50": 0.0,
      "feedback_lag_ms_p95": 0.0,
      "closed_loop": false,
      "duplication_rate_p50": 0.0,
      "deadline_miss_rate_p95": 0.002,
      "tail_ratio_p99_p50": 1.006
    },
    {
      "transport": "quic-datagram",
      "quality": "good",
      "payload": "tiny",
      "payload_bytes": 256,
      "runs": 5,
      "events_per_s_p50": 366.4573892646619,
      "events_per_s_p95": 381.7523921726291,
      "elapsed_s_p95": 0.112438584,
      "sent_total": 198,
      "dropped_total": 1,
      "fallback_total": 1,
      "mode_switch_count_total": 0,
      "effective_parity_rate_p50": 0.0,
      "feedback_lag_ms_p95": 0.0,
      "closed_loop": false,
      "duplication_rate_p50": 0.0,
      "deadline_miss_rate_p95": 0.002,
      "tail_ratio_p99_p50": 1.006
    },
    {
      "transport": "quic-datagram",
      "quality": "poor",
      "payload": "large",
      "payload_bytes": 262144,
      "runs": 5,
      "events_per_s_p50": 120.54592234582366,
      "events_per_s_p95": 121.86936936854592,
      "elapsed_s_p95": 0.335450291,
      "sent_total": 0,
      "dropped_total": 12,
      "fallback_total": 188,
      "mode_switch_count_total": 0,
      "effective_parity_rate_p50": 0.0,
      "feedback_lag_ms_p95": 0.0,
      "closed_loop": false,
      "duplication_rate_p50": 0.0,
      "deadline_miss_rate_p95": 0.03,
      "tail_ratio_p99_p50": 1.09
    },
    {
      "transport": "quic-datagram",
      "quality": "poor",
      "payload": "medium",
      "payload_bytes": 65536,
      "runs": 5,
      "events_per_s_p50": 120.15024788498016,
      "events_per_s_p95": 120.46464720234032,
      "elapsed_s_p95": 0.335474542,
      "sent_total": 0,
      "dropped_total": 12,
      "fallback_total": 188,
      "mode_switch_count_total": 0,
      "effective_parity_rate_p50": 0.0,
      "feedback_lag_ms_p95": 0.0,
      "closed_loop": false,
      "duplication_rate_p50": 0.0,
      "deadline_miss_rate_p95": 0.03,
      "tail_ratio_p99_p50": 1.09
    },
    {
      "transport": "quic-datagram",
      "quality": "poor",
      "payload": "small",
      "payload_bytes": 4096,
      "runs": 5,
      "events_per_s_p50": 120.63421932884398,
      "events_per_s_p95": 122.23576872965664,
      "elapsed_s_p95": 0.332683375,
      "sent_total": 0,
      "dropped_total": 12,
      "fallback_total": 188,
      "mode_switch_count_total": 0,
      "effective_parity_rate_p50": 0.0,
      "feedback_lag_ms_p95": 0.0,
      "closed_loop": false,
      "duplication_rate_p50": 0.0,
      "deadline_miss_rate_p95": 0.03,
      "tail_ratio_p99_p50": 1.09
    },
    {
      "transport": "quic-datagram",
      "quality": "poor",
      "payload": "tiny",
      "payload_bytes": 256,
      "runs": 5,
      "events_per_s_p50": 120.17896161639597,
      "events_per_s_p95": 120.71042600272536,
      "elapsed_s_p95": 0.335277583,
      "sent_total": 188,
      "dropped_total": 9,
      "fallback_total": 3,
      "mode_switch_count_total": 0,
      "effective_parity_rate_p50": 0.0,
      "feedback_lag_ms_p95": 0.0,
      "closed_loop": false,
      "duplication_rate_p50": 0.0,
      "deadline_miss_rate_p95": 0.03,
      "tail_ratio_p99_p50": 1.09
    },
    {
      "transport": "quic-datagram",
      "quality": "very-poor",
      "payload": "large",
      "payload_bytes": 262144,
      "runs": 5,
      "events_per_s_p50": 66.93897822328776,
      "events_per_s_p95": 67.25285465333901,
      "elapsed_s_p95": 0.600666792,
      "sent_total": 0,
      "dropped_total": 0,
      "fallback_total": 200,
      "mode_switch_count_total": 0,
      "effective_parity_rate_p50": 0.0,
      "feedback_lag_ms_p95": 0.0,
      "closed_loop": false,
      "duplication_rate_p50": 0.0,
      "deadline_miss_rate_p95": 0.12,
      "tail_ratio_p99_p50": 1.3599999999999999
    },
    {
      "transport": "quic-datagram",
      "quality": "very-poor",
      "payload": "medium",
      "payload_bytes": 65536,
      "runs": 5,
      "events_per_s_p50": 66.8972950914946,
      "events_per_s_p95": 67.11241896437568,
      "elapsed_s_p95": 0.598656459,
      "sent_total": 0,
      "dropped_total": 0,
      "fallback_total": 200,
      "mode_switch_count_total": 0,
      "effective_parity_rate_p50": 0.0,
      "feedback_lag_ms_p95": 0.0,
      "closed_loop": false,
      "duplication_rate_p50": 0.0,
      "deadline_miss_rate_p95": 0.12,
      "tail_ratio_p99_p50": 1.3599999999999999
    },
    {
      "transport": "quic-datagram",
      "quality": "very-poor",
      "payload": "small",
      "payload_bytes": 4096,
      "runs": 5,
      "events_per_s_p50": 66.97583448599582,
      "events_per_s_p95": 67.24140800677503,
      "elapsed_s_p95": 0.599707583,
      "sent_total": 0,
      "dropped_total": 13,
      "fallback_total": 187,
      "mode_switch_count_total": 0,
      "effective_parity_rate_p50": 0.0,
      "feedback_lag_ms_p95": 0.0,
      "closed_loop": false,
      "duplication_rate_p50": 0.0,
      "deadline_miss_rate_p95": 0.12,
      "tail_ratio_p99_p50": 1.3599999999999999
    },
    {
      "transport": "quic-datagram",
      "quality": "very-poor",
      "payload": "tiny",
      "payload_bytes": 256,
      "runs": 5,
      "events_per_s_p50": 68.02965011753984,
      "events_per_s_p95": 68.31488171434502,
      "elapsed_s_p95": 0.590790959,
      "sent_total": 168,
      "dropped_total": 32,
      "fallback_total": 0,
      "mode_switch_count_total": 0,
      "effective_parity_rate_p50": 0.0,
      "feedback_lag_ms_p95": 0.0,
      "closed_loop": false,
      "duplication_rate_p50": 0.0,
      "deadline_miss_rate_p95": 0.12,
      "tail_ratio_p99_p50": 1.3599999999999999
    },
    {
      "transport": "quic-stream",
      "quality": "excellent",
      "payload": "large",
      "payload_bytes": 262144,
      "runs": 5,
      "events_per_s_p50": 16976.127320954907,
      "events_per_s_p95": 17472.345644930487,
      "elapsed_s_p95": 0.00172525,
      "sent_total": 100,
      "dropped_total": 0,
      "fallback_total": 0,
      "mode_switch_count_total": 0,
      "effective_parity_rate_p50": 0.0,
      "feedback_lag_ms_p95": 0.0,
      "closed_loop": false,
      "duplication_rate_p50": 0.0,
      "deadline_miss_rate_p95": 0.0,
      "tail_ratio_p99_p50": 1.0
    },
    {
      "transport": "quic-stream",
      "quality": "excellent",
      "payload": "medium",
      "payload_bytes": 65536,
      "runs": 5,
      "events_per_s_p50": 3877.096055054764,
      "events_per_s_p95": 31785.991277923993,
      "elapsed_s_p95": 0.005636292,
      "sent_total": 100,
      "dropped_total": 0,
      "fallback_total": 0,
      "mode_switch_count_total": 0,
      "effective_parity_rate_p50": 0.0,
      "feedback_lag_ms_p95": 0.0,
      "closed_loop": false,
      "duplication_rate_p50": 0.0,
      "deadline_miss_rate_p95": 0.0,
      "tail_ratio_p99_p50": 1.0
    },
    {
      "transport": "quic-stream",
      "quality": "excellent",
      "payload": "small",
      "payload_bytes": 4096,
      "runs": 5,
      "events_per_s_p50": 98360.81698494586,
      "events_per_s_p95": 113101.06145346175,
      "elapsed_s_p95": 0.000456083,
      "sent_total": 100,
      "dropped_total": 0,
      "fallback_total": 0,
      "mode_switch_count_total": 0,
      "effective_parity_rate_p50": 0.0,
      "feedback_lag_ms_p95": 0.0,
      "closed_loop": false,
      "duplication_rate_p50": 0.0,
      "deadline_miss_rate_p95": 0.0,
      "tail_ratio_p99_p50": 1.0
    },
    {
      "transport": "quic-stream",
      "quality": "excellent",
      "payload": "tiny",
      "payload_bytes": 256,
      "runs": 5,
      "events_per_s_p50": 42171.85028993147,
      "events_per_s_p95": 67902.0309497457,
      "elapsed_s_p95": 0.006994459,
      "sent_total": 100,
      "dropped_total": 0,
      "fallback_total": 0,
      "mode_switch_count_total": 0,
      "effective_parity_rate_p50": 0.0,
      "feedback_lag_ms_p95": 0.0,
      "closed_loop": false,
      "duplication_rate_p50": 0.0,
      "deadline_miss_rate_p95": 0.0,
      "tail_ratio_p99_p50": 1.0
    },
    {
      "transport": "quic-stream",
      "quality": "good",
      "payload": "large",
      "payload_bytes": 262144,
      "runs": 5,
      "events_per_s_p50": 242.71120650308757,
      "events_per_s_p95": 323.42006106397145,
      "elapsed_s_p95": 0.082934375,
      "sent_total": 100,
      "dropped_total": 0,
      "fallback_total": 0,
      "mode_switch_count_total": 0,
      "effective_parity_rate_p50": 0.0,
      "feedback_lag_ms_p95": 0.0,
      "closed_loop": false,
      "duplication_rate_p50": 0.0,
      "deadline_miss_rate_p95": 0.002,
      "tail_ratio_p99_p50": 1.006
    },
    {
      "transport": "quic-stream",
      "quality": "good",
      "payload": "medium",
      "payload_bytes": 65536,
      "runs": 5,
      "events_per_s_p50": 370.8614183594945,
      "events_per_s_p95": 376.06914813512293,
      "elapsed_s_p95": 0.055190292,
      "sent_total": 100,
      "dropped_total": 0,
      "fallback_total": 0,
      "mode_switch_count_total": 0,
      "effective_parity_rate_p50": 0.0,
      "feedback_lag_ms_p95": 0.0,
      "closed_loop": false,
      "duplication_rate_p50": 0.0,
      "deadline_miss_rate_p95": 0.002,
      "tail_ratio_p99_p50": 1.006
    },
    {
      "transport": "quic-stream",
      "quality": "good",
      "payload": "small",
      "payload_bytes": 4096,
      "runs": 5,
      "events_per_s_p50": 357.23136759331,
      "events_per_s_p95": 368.4971763903859,
      "elapsed_s_p95": 0.058527,
      "sent_total": 100,
      "dropped_total": 0,
      "fallback_total": 0,
      "mode_switch_count_total": 0,
      "effective_parity_rate_p50": 0.0,
      "feedback_lag_ms_p95": 0.0,
      "closed_loop": false,
      "duplication_rate_p50": 0.0,
      "deadline_miss_rate_p95": 0.002,
      "tail_ratio_p99_p50": 1.006
    },
    {
      "transport": "quic-stream",
      "quality": "good",
      "payload": "tiny",
      "payload_bytes": 256,
      "runs": 5,
      "events_per_s_p50": 352.8368799643818,
      "events_per_s_p95": 367.70591880773856,
      "elapsed_s_p95": 0.057115416,
      "sent_total": 100,
      "dropped_total": 0,
      "fallback_total": 0,
      "mode_switch_count_total": 0,
      "effective_parity_rate_p50": 0.0,
      "feedback_lag_ms_p95": 0.0,
      "closed_loop": false,
      "duplication_rate_p50": 0.0,
      "deadline_miss_rate_p95": 0.002,
      "tail_ratio_p99_p50": 1.006
    },
    {
      "transport": "quic-stream",
      "quality": "poor",
      "payload": "large",
      "payload_bytes": 262144,
      "runs": 5,
      "events_per_s_p50": 126.01014854233823,
      "events_per_s_p95": 128.07783689751113,
      "elapsed_s_p95": 0.161224917,
      "sent_total": 100,
      "dropped_total": 0,
      "fallback_total": 0,
      "mode_switch_count_total": 0,
      "effective_parity_rate_p50": 0.0,
      "feedback_lag_ms_p95": 0.0,
      "closed_loop": false,
      "duplication_rate_p50": 0.0,
      "deadline_miss_rate_p95": 0.03,
      "tail_ratio_p99_p50": 1.09
    },
    {
      "transport": "quic-stream",
      "quality": "poor",
      "payload": "medium",
      "payload_bytes": 65536,
      "runs": 5,
      "events_per_s_p50": 120.54586204087833,
      "events_per_s_p95": 122.17079171254434,
      "elapsed_s_p95": 0.167376833,
      "sent_total": 100,
      "dropped_total": 0,
      "fallback_total": 0,
      "mode_switch_count_total": 0,
      "effective_parity_rate_p50": 0.0,
      "feedback_lag_ms_p95": 0.0,
      "closed_loop": false,
      "duplication_rate_p50": 0.0,
      "deadline_miss_rate_p95": 0.03,
      "tail_ratio_p99_p50": 1.09
    },
    {
      "transport": "quic-stream",
      "quality": "poor",
      "payload": "small",
      "payload_bytes": 4096,
      "runs": 5,
      "events_per_s_p50": 122.72890769946676,
      "events_per_s_p95": 123.5909664272864,
      "elapsed_s_p95": 0.168085959,
      "sent_total": 100,
      "dropped_total": 0,
      "fallback_total": 0,
      "mode_switch_count_total": 0,
      "effective_parity_rate_p50": 0.0,
      "feedback_lag_ms_p95": 0.0,
      "closed_loop": false,
      "duplication_rate_p50": 0.0,
      "deadline_miss_rate_p95": 0.03,
      "tail_ratio_p99_p50": 1.09
    },
    {
      "transport": "quic-stream",
      "quality": "poor",
      "payload": "tiny",
      "payload_bytes": 256,
      "runs": 5,
      "events_per_s_p50": 121.41367969386076,
      "events_per_s_p95": 124.2592015880326,
      "elapsed_s_p95": 0.167768,
      "sent_total": 100,
      "dropped_total": 0,
      "fallback_total": 0,
      "mode_switch_count_total": 0,
      "effective_parity_rate_p50": 0.0,
      "feedback_lag_ms_p95": 0.0,
      "closed_loop": false,
      "duplication_rate_p50": 0.0,
      "deadline_miss_rate_p95": 0.03,
      "tail_ratio_p99_p50": 1.09
    },
    {
      "transport": "quic-stream",
      "quality": "very-poor",
      "payload": "large",
      "payload_bytes": 262144,
      "runs": 5,
      "events_per_s_p50": 67.43234225671026,
      "events_per_s_p95": 68.28014539314695,
      "elapsed_s_p95": 0.296926375,
      "sent_total": 100,
      "dropped_total": 0,
      "fallback_total": 0,
      "mode_switch_count_total": 0,
      "effective_parity_rate_p50": 0.0,
      "feedback_lag_ms_p95": 0.0,
      "closed_loop": false,
      "duplication_rate_p50": 0.0,
      "deadline_miss_rate_p95": 0.12,
      "tail_ratio_p99_p50": 1.3599999999999999
    },
    {
      "transport": "quic-stream",
      "quality": "very-poor",
      "payload": "medium",
      "payload_bytes": 65536,
      "runs": 5,
      "events_per_s_p50": 67.11936823572475,
      "events_per_s_p95": 67.8575478576468,
      "elapsed_s_p95": 0.29911225,
      "sent_total": 100,
      "dropped_total": 0,
      "fallback_total": 0,
      "mode_switch_count_total": 0,
      "effective_parity_rate_p50": 0.0,
      "feedback_lag_ms_p95": 0.0,
      "closed_loop": false,
      "duplication_rate_p50": 0.0,
      "deadline_miss_rate_p95": 0.12,
      "tail_ratio_p99_p50": 1.3599999999999999
    },
    {
      "transport": "quic-stream",
      "quality": "very-poor",
      "payload": "small",
      "payload_bytes": 4096,
      "runs": 5,
      "events_per_s_p50": 67.69691968556256,
      "events_per_s_p95": 68.05552869725211,
      "elapsed_s_p95": 0.296765292,
      "sent_total": 100,
      "dropped_total": 0,
      "fallback_total": 0,
      "mode_switch_count_total": 0,
      "effective_parity_rate_p50": 0.0,
      "feedback_lag_ms_p95": 0.0,
      "closed_loop": false,
      "duplication_rate_p50": 0.0,
      "deadline_miss_rate_p95": 0.12,
      "tail_ratio_p99_p50": 1.3599999999999999
    },
    {
      "transport": "quic-stream",
      "quality": "very-poor",
      "payload": "tiny",
      "payload_bytes": 256,
      "runs": 5,
      "events_per_s_p50": 68.12743236223356,
      "events_per_s_p95": 68.70171639078198,
      "elapsed_s_p95": 0.29584825,
      "sent_total": 100,
      "dropped_total": 0,
      "fallback_total": 0,
      "mode_switch_count_total": 0,
      "effective_parity_rate_p50": 0.0,
      "feedback_lag_ms_p95": 0.0,
      "closed_loop": false,
      "duplication_rate_p50": 0.0,
      "deadline_miss_rate_p95": 0.12,
      "tail_ratio_p99_p50": 1.3599999999999999
    },
    {
      "transport": "sse",
      "quality": "excellent",
      "payload": "large",
      "payload_bytes": 262144,
      "runs": 5,
      "events_per_s_p50": 9743.95010318031,
      "events_per_s_p95": 54353.98029668214,
      "elapsed_s_p95": 0.00702375,
      "sent_total": 300,
      "dropped_total": 0,
      "fallback_total": 0,
      "mode_switch_count_total": 0,
      "effective_parity_rate_p50": 0.0,
      "feedback_lag_ms_p95": 0.0,
      "closed_loop": false,
      "duplication_rate_p50": 0.0,
      "deadline_miss_rate_p95": 0.0,
      "tail_ratio_p99_p50": 1.0
    },
    {
      "transport": "sse",
      "quality": "excellent",
      "payload": "medium",
      "payload_bytes": 65536,
      "runs": 5,
      "events_per_s_p50": 138778.54067425555,
      "events_per_s_p95": 140002.83505740992,
      "elapsed_s_p95": 0.000693,
      "sent_total": 400,
      "dropped_total": 0,
      "fallback_total": 0,
      "mode_switch_count_total": 0,
      "effective_parity_rate_p50": 0.0,
      "feedback_lag_ms_p95": 0.0,
      "closed_loop": false,
      "duplication_rate_p50": 0.0,
      "deadline_miss_rate_p95": 0.0,
      "tail_ratio_p99_p50": 1.0
    },
    {
      "transport": "sse",
      "quality": "excellent",
      "payload": "small",
      "payload_bytes": 4096,
      "runs": 5,
      "events_per_s_p50": 141559.64757310142,
      "events_per_s_p95": 173035.52765453802,
      "elapsed_s_p95": 0.001740125,
      "sent_total": 500,
      "dropped_total": 0,
      "fallback_total": 0,
      "mode_switch_count_total": 0,
      "effective_parity_rate_p50": 0.0,
      "feedback_lag_ms_p95": 0.0,
      "closed_loop": false,
      "duplication_rate_p50": 0.0,
      "deadline_miss_rate_p95": 0.0,
      "tail_ratio_p99_p50": 1.0
    },
    {
      "transport": "sse",
      "quality": "excellent",
      "payload": "tiny",
      "payload_bytes": 256,
      "runs": 5,
      "events_per_s_p50": 259623.3730268624,
      "events_per_s_p95": 335274.1984152706,
      "elapsed_s_p95": 0.000819709,
      "sent_total": 600,
      "dropped_total": 0,
      "fallback_total": 0,
      "mode_switch_count_total": 0,
      "effective_parity_rate_p50": 0.0,
      "feedback_lag_ms_p95": 0.0,
      "closed_loop": false,
      "duplication_rate_p50": 0.0,
      "deadline_miss_rate_p95": 0.0,
      "tail_ratio_p99_p50": 1.0
    },
    {
      "transport": "sse",
      "quality": "good",
      "payload": "large",
      "payload_bytes": 262144,
      "runs": 5,
      "events_per_s_p50": 354.74026677402213,
      "events_per_s_p95": 355.4923569143263,
      "elapsed_s_p95": 0.169846208,
      "sent_total": 300,
      "dropped_total": 0,
      "fallback_total": 0,
      "mode_switch_count_total": 0,
      "effective_parity_rate_p50": 0.0,
      "feedback_lag_ms_p95": 0.0,
      "closed_loop": false,
      "duplication_rate_p50": 0.0,
      "deadline_miss_rate_p95": 0.002,
      "tail_ratio_p99_p50": 1.006
    },
    {
      "transport": "sse",
      "quality": "good",
      "payload": "medium",
      "payload_bytes": 65536,
      "runs": 5,
      "events_per_s_p50": 354.53855462085454,
      "events_per_s_p95": 355.1920094300637,
      "elapsed_s_p95": 0.226520167,
      "sent_total": 400,
      "dropped_total": 0,
      "fallback_total": 0,
      "mode_switch_count_total": 0,
      "effective_parity_rate_p50": 0.0,
      "feedback_lag_ms_p95": 0.0,
      "closed_loop": false,
      "duplication_rate_p50": 0.0,
      "deadline_miss_rate_p95": 0.002,
      "tail_ratio_p99_p50": 1.006
    },
    {
      "transport": "sse",
      "quality": "good",
      "payload": "small",
      "payload_bytes": 4096,
      "runs": 5,
      "events_per_s_p50": 355.99619974056776,
      "events_per_s_p95": 357.10411772294344,
      "elapsed_s_p95": 0.282471334,
      "sent_total": 500,
      "dropped_total": 0,
      "fallback_total": 0,
      "mode_switch_count_total": 0,
      "effective_parity_rate_p50": 0.0,
      "feedback_lag_ms_p95": 0.0,
      "closed_loop": false,
      "duplication_rate_p50": 0.0,
      "deadline_miss_rate_p95": 0.002,
      "tail_ratio_p99_p50": 1.006
    },
    {
      "transport": "sse",
      "quality": "good",
      "payload": "tiny",
      "payload_bytes": 256,
      "runs": 5,
      "events_per_s_p50": 314.67166470160765,
      "events_per_s_p95": 351.1353257022868,
      "elapsed_s_p95": 0.387182959,
      "sent_total": 600,
      "dropped_total": 0,
      "fallback_total": 0,
      "mode_switch_count_total": 0,
      "effective_parity_rate_p50": 0.0,
      "feedback_lag_ms_p95": 0.0,
      "closed_loop": false,
      "duplication_rate_p50": 0.0,
      "deadline_miss_rate_p95": 0.002,
      "tail_ratio_p99_p50": 1.006
    },
    {
      "transport": "sse",
      "quality": "poor",
      "payload": "large",
      "payload_bytes": 262144,
      "runs": 5,
      "events_per_s_p50": 120.0278565450584,
      "events_per_s_p95": 120.10077439798341,
      "elapsed_s_p95": 0.502357458,
      "sent_total": 300,
      "dropped_total": 0,
      "fallback_total": 0,
      "mode_switch_count_total": 0,
      "effective_parity_rate_p50": 0.0,
      "feedback_lag_ms_p95": 0.0,
      "closed_loop": false,
      "duplication_rate_p50": 0.0,
      "deadline_miss_rate_p95": 0.03,
      "tail_ratio_p99_p50": 1.09
    },
    {
      "transport": "sse",
      "quality": "poor",
      "payload": "medium",
      "payload_bytes": 65536,
      "runs": 5,
      "events_per_s_p50": 119.97452041122767,
      "events_per_s_p95": 120.13245353830432,
      "elapsed_s_p95": 0.668214708,
      "sent_total": 400,
      "dropped_total": 0,
      "fallback_total": 0,
      "mode_switch_count_total": 0,
      "effective_parity_rate_p50": 0.0,
      "feedback_lag_ms_p95": 0.0,
      "closed_loop": false,
      "duplication_rate_p50": 0.0,
      "deadline_miss_rate_p95": 0.03,
      "tail_ratio_p99_p50": 1.09
    },
    {
      "transport": "sse",
      "quality": "poor",
      "payload": "small",
      "payload_bytes": 4096,
      "runs": 5,
      "events_per_s_p50": 120.15515043412218,
      "events_per_s_p95": 120.72918617511979,
      "elapsed_s_p95": 0.835836583,
      "sent_total": 500,
      "dropped_total": 0,
      "fallback_total": 0,
      "mode_switch_count_total": 0,
      "effective_parity_rate_p50": 0.0,
      "feedback_lag_ms_p95": 0.0,
      "closed_loop": false,
      "duplication_rate_p50": 0.0,
      "deadline_miss_rate_p95": 0.03,
      "tail_ratio_p99_p50": 1.09
    },
    {
      "transport": "sse",
      "quality": "poor",
      "payload": "tiny",
      "payload_bytes": 256,
      "runs": 5,
      "events_per_s_p50": 120.42503510354649,
      "events_per_s_p95": 120.63365335605256,
      "elapsed_s_p95": 1.001816667,
      "sent_total": 600,
      "dropped_total": 0,
      "fallback_total": 0,
      "mode_switch_count_total": 0,
      "effective_parity_rate_p50": 0.0,
      "feedback_lag_ms_p95": 0.0,
      "closed_loop": false,
      "duplication_rate_p50": 0.0,
      "deadline_miss_rate_p95": 0.03,
      "tail_ratio_p99_p50": 1.09
    },
    {
      "transport": "sse",
      "quality": "very-poor",
      "payload": "large",
      "payload_bytes": 262144,
      "runs": 5,
      "events_per_s_p50": 67.24011901604167,
      "events_per_s_p95": 67.30472797665152,
      "elapsed_s_p95": 0.89539875,
      "sent_total": 300,
      "dropped_total": 0,
      "fallback_total": 0,
      "mode_switch_count_total": 0,
      "effective_parity_rate_p50": 0.0,
      "feedback_lag_ms_p95": 0.0,
      "closed_loop": false,
      "duplication_rate_p50": 0.0,
      "deadline_miss_rate_p95": 0.12,
      "tail_ratio_p99_p50": 1.3599999999999999
    },
    {
      "transport": "sse",
      "quality": "very-poor",
      "payload": "medium",
      "payload_bytes": 65536,
      "runs": 5,
      "events_per_s_p50": 67.06139281902415,
      "events_per_s_p95": 67.31232978741683,
      "elapsed_s_p95": 1.193361292,
      "sent_total": 400,
      "dropped_total": 0,
      "fallback_total": 0,
      "mode_switch_count_total": 0,
      "effective_parity_rate_p50": 0.0,
      "feedback_lag_ms_p95": 0.0,
      "closed_loop": false,
      "duplication_rate_p50": 0.0,
      "deadline_miss_rate_p95": 0.12,
      "tail_ratio_p99_p50": 1.3599999999999999
    },
    {
      "transport": "sse",
      "quality": "very-poor",
      "payload": "small",
      "payload_bytes": 4096,
      "runs": 5,
      "events_per_s_p50": 67.1837595504855,
      "events_per_s_p95": 67.39068218972304,
      "elapsed_s_p95": 1.490618959,
      "sent_total": 500,
      "dropped_total": 0,
      "fallback_total": 0,
      "mode_switch_count_total": 0,
      "effective_parity_rate_p50": 0.0,
      "feedback_lag_ms_p95": 0.0,
      "closed_loop": false,
      "duplication_rate_p50": 0.0,
      "deadline_miss_rate_p95": 0.12,
      "tail_ratio_p99_p50": 1.3599999999999999
    },
    {
      "transport": "sse",
      "quality": "very-poor",
      "payload": "tiny",
      "payload_bytes": 256,
      "runs": 5,
      "events_per_s_p50": 67.25590940166731,
      "events_per_s_p95": 67.49887943844641,
      "elapsed_s_p95": 1.7910359580000002,
      "sent_total": 600,
      "dropped_total": 0,
      "fallback_total": 0,
      "mode_switch_count_total": 0,
      "effective_parity_rate_p50": 0.0,
      "feedback_lag_ms_p95": 0.0,
      "closed_loop": false,
      "duplication_rate_p50": 0.0,
      "deadline_miss_rate_p95": 0.12,
      "tail_ratio_p99_p50": 1.3599999999999999
    }
  ]
}